{"result": "success", "provider": "https://www.exchangerate-api.com", "documentation": "https://www.exchangerate-api.com/docs/free", "terms_of_use": "https://www.exchangerate-api.com/terms", "time_last_update_unix": 1630195351, "time_last_update_utc": "Sun, 29 Aug 2021 00:02:31 +0000", "time_next_update_unix": 1630283261, "time_next_update_utc": "Mon, 30 Aug 2021 00:27:41 +0000", "time_eol_unix": 0, "base_code": "DKK", "rates": {"DKK": 1, "AED": 0.58, "AFN": 12.61, "ALL": 16.33, "AMD": 77.8, "ANG": 0.283, "AOA": 100.8, "ARS": 15.37, "AUD": 0.217, "AWG": 0.283, "AZN": 0.268, "BAM": 0.262, "BBD": 0.316, "BDT": 13.37, "BGN": 0.262, "BHD": 0.0594, "BIF": 311.39, "BMD": 0.158, "BND": 0.213, "BOB": 1.08, "BRL": 0.826, "BSD": 0.158, "BTN": 11.66, "BWP": 1.77, "BYN": 0.396, "BZD": 0.316, "CAD": 0.199, "CDF": 314, "CHF": 0.144, "CLP": 123.81, "CNY": 1.02, "COP": 615.39, "CRC": 98.07, "CUC": 0.158, "CUP": 4.07, "CVE": 14.78, "CZK": 3.42, "DJF": 28.06, "DOP": 8.96, "DZD": 21.38, "EGP": 2.47, "ERN": 2.37, "ETB": 7.23, "EUR": 0.134, "FJD": 0.331, "FKP": 0.115, "FOK": 1, "GBP": 0.115, "GEL": 0.491, "GGP": 0.115, "GHS": 0.949, "GIP": 0.115, "GMD": 8.22, "GNF": 1549.41, "GTQ": 1.22, "GYD": 33.05, "HKD": 1.23, "HNL": 3.75, "HRK": 1.01, "HTG": 15.25, "HUF": 46.86, "IDR": 2301.83, "ILS": 0.51, "IMP": 0.115, "INR": 11.65, "IQD": 230.64, "IRR": 6557.5, "ISK": 19.96, "JMD": 23.96, "JOD": 0.112, "JPY": 17.35, "KES": 17.29, "KGS": 13.35, "KHR": 644.78, "KID": 0.217, "KMF": 65.94, "KRW": 184.22, "KWD": 0.0473, "KYD": 0.132, "KZT": 67.25, "LAK": 1507.9, "LBP": 238.04, "LKR": 31.51, "LRD": 27.1, "LSL": 2.34, "LYD": 0.716, "MAD": 1.41, "MDL": 2.79, "MGA": 618.04, "MKD": 8.24, "MMK": 257.95, "MNT": 450.97, "MOP": 1.27, "MRU": 5.71, "MUR": 6.7, "MVR": 2.41, "MWK": 128.01, "MXN": 3.2, "MYR": 0.66, "MZN": 10.1, "NAD": 2.34, "NGN": 67.83, "NIO": 5.53, "NOK": 1.38, "NPR": 18.66, "NZD": 0.226, "OMR": 0.0607, "PAB": 0.158, "PEN": 0.643, "PGK": 0.554, "PHP": 7.87, "PKR": 26.13, "PLN": 0.613, "PYG": 1113.62, "QAR": 0.575, "RON": 0.66, "RSD": 15.76, "RUB": 11.67, "RWF": 159.01, "SAR": 0.592, "SBD": 1.25, "SCR": 2.25, "SDG": 69.9, "SEK": 1.37, "SGD": 0.212, "SHP": 0.115, "SLL": 1631.61, "SOS": 91.44, "SRD": 3.39, "SSP": 28.05, "STN": 3.28, "SYP": 199.15, "SZL": 2.34, "THB": 5.15, "TJS": 1.78, "TMT": 0.552, "TND": 0.44, "TOP": 0.354, "TRY": 1.32, "TTD": 1.09, "TVD": 0.217, "TWD": 4.4, "TZS": 365.52, "UAH": 4.23, "UGX": 557.52, "USD": 0.158, "UYU": 6.73, "UZS": 1691.4, "VES": 652649.58, "VND": 3574.82, "VUV": 17.67, "WST": 0.402, "XAF": 87.93, "XCD": 0.426, "XDR": 0.111, "XOF": 87.93, "XPF": 16, "YER": 39.56, "ZAR": 2.34, "ZMW": 2.52}}